africastalking/Airtime.py
africastalking/Application.py
africastalking/Insights.py
africastalking/MobileData.py
africastalking/SMS.py
africastalking/Service.py
africastalking/Token.py
africastalking/Voice.py
africastalking/__init__.py
africastalking-1.2.9.data/data/README.md
africastalking-1.2.9.dist-info/LICENSE
africastalking-1.2.9.dist-info/METADATA
africastalking-1.2.9.dist-info/WHEEL
africastalking-1.2.9.dist-info/top_level.txt
africastalking-1.2.9.dist-info/RECORD
