Metadata-Version: 2.1
Name: africastalking
Version: 1.2.9
Summary: Official Africa's Talking Python SDK
Home-page: https://github.com/AfricasTalkingLtd/africastalking-python
Download-URL: https://codeload.github.com/AfricasTalkingLtd/africastalking-python/tar.gz/1.2.9
Author: Africa's Talking
Author-email: info@africastalking.com
License: MIT
Keywords: ussd voice sms mpesa card bank b2b b2c sender_id payments airtime africastalking
Requires-Python: >=2.7.10
License-File: LICENSE
Requires-Dist: requests>=v2.18.4
Requires-Dist: schema>=0.6.7
